{
    "header": {
        "logo": "/images/logo.png",
        "navItems": [
            {
                "id": 1,
                "label": "Products",
                "link": "/products"
            },
            {
                "id": 2,
                "label": "Shipping Details",
                "link": "/shipping"
            },
            {
                "id": 3,
                "label": "Contact",
                "link": "/contact-us"
            }
        ],
        "ctaBtn": {
            "label": "Order Now",
            "link": "tel: +91-987654321",
            "show": true
        }
    },
    "footer": {
        "logo": "/images/logo.png",
        "fssaiLogo": "/images/fssai.jpeg",
        "address": {
            "title": "Address",
            "content": "Babu Nagar, Anuppanadi,\nTeppakulam,Madurai, 625009"
        },
        "socialLinks": {
            "title": "Follow Us On",
            "items": [
                {
                    "id": 1,
                    "platform": "instagram",
                    "link": "https://instagram.com/as_masalas"
                },
                {
                    "id": 2,
                    "platform": "youtube",
                    "link": "https://instagram.com/as_masalas"
                },
                {
                    "id": 3,
                    "platform": "whatsapp",
                    "link": "https://instagram.com/as_masalas"
                },
                {
                    "id": 4,
                    "platform": "x-twitter",
                    "link": "https://instagram.com/as_masalas"
                }
            ]
        },
        "linkColumns": [
            {
                "id": 1,
                "title": "Quick Links",
                "items": [
                    {
                        "id": 1,
                        "label": "Products",
                        "url": "/products"
                    },
                    {
                        "id": 2,
                        "label": "Shipping Details",
                        "url": "/shipping"
                    },
                    {
                        "id": 3,
                        "label": "Contact",
                        "url": "/contact-us"
                    }
                ]
            },
            {
                "id": 2,
                "title": "Contact Us",
                "items": [
                    {
                        "id": 1,
                        "label": "asmasala25@gmail.com",
                        "url": "mailto:asmasala25@gmail.com"
                    },
                    {
                        "id": 2,
                        "label": "+91-8190932148",
                        "url": "tel:+91-8190932148"
                    },
                    {
                        "id": 3,
                        "label": "+91-7904478532",
                        "url": "tel:+91-7904478532"
                    }
                ]
            }
        ],
        "copyRight": "© 2026 A.S. Masala’s. All rights reserved."
    },
    "homePage": {
        "banner": {
            "type": "image",
            "imageSlides": [
                {
                    "id": "1",
                    "src": "/images/banner_two.png",
                    "alt": "Banner Image"
                },
                {
                    "id": "2",
                    "src": "/images/banner_two.png",
                    "alt": "Banner Image"
                },
                {
                    "id": "3",
                    "src": "/images/banner_two.png",
                    "alt": "Banner Image"
                },
                {
                    "id": "4",
                    "src": "/images/banner_two.png",
                    "alt": "Banner Image"
                }
            ]
        },
        "iconColumn": {
            "cards": [
                {
                    "id": "1",
                    "title": "Secure Payment",
                    "desc": "Choose your way to pay secure online payment or convenient cash on delivery at your doorstep.",
                    "src": "/images/card.svg",
                    "alt": "icon"
                },
                {
                    "id": "2",
                    "title": "Free Shipping",
                    "desc": "Shop for ₹999 or more and enjoy Free Shipping. Applicable for specific locations.",
                    "src": "/images/truck.svg",
                    "alt": "icon"
                },
                {
                    "id": "3",
                    "title": "Delivered with Care",
                    "desc": "From packaging to delivery, we handle every product with love and care.",
                    "src": "/images/box.svg",
                    "alt": "icon"
                },
                {
                    "id": "4",
                    "title": "Excellent Service",
                    "desc": "Your satisfaction is our top priority. Count on us for excellent service from order to delivery.",
                    "src": "/images/heart.svg",
                    "alt": "icon"
                }
            ]
        },
        "parallaxBanner": {
            "src" : "/images/parallax2.jpg",
            "alt" : "page Banner Image",
            "title" : ["Offer","Get upto 20% off"],
            "desc" : "For All The Spicy Masala's"
        },
        "textAndImage1" : {
            "imageDirection" : "leftToRight",
            "src" : "/images/sambar_masala05.png",
            "alt" : "Masala",
            "title" : "Product Title",
            "desc" : "Lorem ipsum dolor simet Lorem ipsum dolor simet Lorem ipsum dolor simet Lorem ipsum dolor simet Lorem ipsum dolor simet Lorem ipsum dolor simet"
        }
    }
}